{
  "div": {
    "style": [
      "class",
      "width",
      "height",
      "margin",
      "padding",
      "fontSize",
      "lineHeight",
      "color",
      "background"
    ]
  },
  "span": {
    "style": [
      "class",
      "width",
      "height",
      "margin",
      "padding",
      "fontSize",
      "lineHeight",
      "color",
      "background"
    ]
  },
  "a": {
    "style": [
      "class",
      "width",
      "height",
      "margin",
      "padding",
      "fontSize",
      "lineHeight",
      "color",
      "background"
    ]
  }
}
